cctexconvert/__init__.py
cctexconvert/cli.py
cctexconvert/converter.py
cctexconvert/texturemap.py
cctexconvert-0.0.2.dist-info/LICENSE
cctexconvert-0.0.2.dist-info/METADATA
cctexconvert-0.0.2.dist-info/WHEEL
cctexconvert-0.0.2.dist-info/entry_points.txt
cctexconvert-0.0.2.dist-info/top_level.txt
cctexconvert-0.0.2.dist-info/RECORD
