Metadata-Version: 2.1
Name: cctexconvert
Version: 0.0.2
Summary: Converts Minecraft texture packs into ClassiCube texture packs
Home-page: https://github.com/Fam0r/CCTexConvert
Author: Fam0r
Author-email: fam0r@mailbox.org
License: wtfpl
Platform: UNKNOWN
Classifier: Environment :: Console
Classifier: License :: Public Domain
Classifier: Operating System :: OS Independent
Classifier: Programming Language :: Python :: 3
Classifier: Topic :: Utilities
License-File: LICENSE
Requires-Dist: Pillow (>=8.3.1)
